README.md
setup.cfg
setup.py
amundsen_common/__init__.py
amundsen_common/py.typed
amundsen_common/log/__init__.py
amundsen_common/log/action_log.py
amundsen_common/log/action_log_callback.py
amundsen_common/log/action_log_model.py
amundsen_common/log/auth_caller_retrieval.py
amundsen_common/log/caller_retrieval.py
amundsen_common/log/http_header_caller_retrieval.py
amundsen_common/models/__init__.py
amundsen_common/models/index_map.py
amundsen_common/models/popular_table.py
amundsen_common/models/table.py
amundsen_common/models/user.py
amundsen_common_rudeserver.egg-info/PKG-INFO
amundsen_common_rudeserver.egg-info/SOURCES.txt
amundsen_common_rudeserver.egg-info/dependency_links.txt
amundsen_common_rudeserver.egg-info/requires.txt
amundsen_common_rudeserver.egg-info/top_level.txt