Metadata-Version: 2.1
Name: amundsen-common-rudeserver
Version: 0.2.7
Summary: Common code library for Gusto Amundsen development
Home-page: https://github.com/lyft/amundsencommon
Maintainer: Team Lodestar
Maintainer-email: epd-data-platform-eng@gusto.com
License: UNKNOWN
Platform: UNKNOWN
Requires-Python: >=3.6
